{
  "accounts": [
    {
      "id": 1,
      "name": "LTB"
    },
    {
      "id": 2,
      "name": "Bitso"
    },
    {
      "id": 3,
      "name": "GBM"
    },
    {
      "id": 4,
      "name": "BANAMEX"
    },
    {
      "id": 5,
      "name": "SANTANDER"
    },
    {
      "id": 6,
      "name": "CETES"
    },
    {
      "id": 7,
      "name": "BRIQ"
    },
    {
      "id": 8,
      "name": "NU"
    }
  ],
  "incomes": {
    "2024-1-1": [
      128486.10
    ],
    "2024-2-1": [
      127565.75
    ],
    "2024-3-1": [
      37862.74,
      2746.12,
      48822.19
    ],
    "2024-4-1": [
      38610.14,
      37862.74
    ],
    "2024-5-1": [
      37862.74,
      65970.87
    ],
    "2024-6-1": [
      37885.17,
      12544.53,
      37862.74
    ],
    "2024-7-1": [
      42657.98,
      679,
      37862.74
    ]
  },
  "balance": [
    {
      "account": {
        "id": 1,
        "name": "LTB"
      },
      "amount": 1000000,
      "date": "2022-1-1"
    },
    {
      "account": {
        "id": 2,
        "name": "Bitso"
      },
      "amount": 9206.71,
      "date": "2022-1-1"
    },
    {
      "account": {
        "id": 3,
        "name": "GBM"
      },
      "amount": 3993.77,
      "date": "2022-1-1"
    },
    {
      "account": {
        "id": 4,
        "name": "BANAMEX"
      },
      "amount": 10614.59,
      "date": "2022-1-1"
    },
    {
      "account": {
        "id": 5,
        "name": "SANTANDER"
      },
      "amount": 11804.87,
      "date": "2022-1-1"
    },
    {
      "account": {
        "id": 3,
        "name": "GBM"
      },
      "amount": 1000,
      "date": "2022-1-6"
    },
    {
      "account": {
        "id": 2,
        "name": "Bitso"
      },
      "amount": 3000,
      "date": "2022-1-6"
    },
    {
      "account": {
        "id": 2,
        "name": "Bitso"
      },
      "amount": 2000,
      "date": "2022-1-14"
    },
    {
      "account": {
        "id": 3,
        "name": "GBM"
      },
      "amount": 1000,
      "date": "2022-1-14"
    },
    {
      "account": {
        "id": 2,
        "name": "Bitso"
      },
      "amount": 3000,
      "date": "2022-1-28"
    },
    {
      "account": {
        "id": 3,
        "name": "GBM"
      },
      "amount": 2330,
      "date": "2022-1-28"
    },
    {
      "account": {
        "id": 4,
        "name": "BANAMEX"
      },
      "amount": 10057.11,
      "date": "2022-2-1"
    },
    {
      "account": {
        "id": 5,
        "name": "SANTANDER"
      },
      "amount": 36317.02,
      "date": "2022-2-1"
    },
    {
      "account": {
        "id": 2,
        "name": "Bitso"
      },
      "amount": 14950,
      "date": "2022-2-1"
    },
    {
      "account": {
        "id": 3,
        "name": "GBM"
      },
      "amount": 8095.17,
      "date": "2022-2-1"
    },
    {
      "account": {
        "id": 6,
        "name": "CETES"
      },
      "amount": 3000,
      "date": "2022-2-1"
    },
    {
      "account": {
        "id": 7,
        "name": "BRIQ"
      },
      "amount": 200000,
      "date": "2022-1-1"
    },
    {
      "account": {
        "id": 1,
        "name": "LTB"
      },
      "amount": 1000000,
      "date": "2022-2-1"
    },
    {
      "account": {
        "id": 7,
        "name": "BRIQ"
      },
      "amount": 200000,
      "date": "2022-2-1"
    },
    {
      "account": {
        "id": 3,
        "name": "GBM"
      },
      "amount": 2370,
      "date": "2022-2-19"
    },
    {
      "account": {
        "id": 2,
        "name": "Bitso"
      },
      "amount": 3000,
      "date": "2022-2-22"
    },
    {
      "account": {
        "id": 2,
        "name": "Bitso"
      },
      "amount": 5000,
      "date": "2022-2-24"
    },
    {
      "account": {
        "id": 1,
        "name": "LTB"
      },
      "amount": 1000000,
      "date": "2022-3-1"
    },
    {
      "account": {
        "id": 4,
        "name": "BANAMEX"
      },
      "amount": 87.11,
      "date": "2022-3-1"
    },
    {
      "account": {
        "id": 5,
        "name": "SANTANDER"
      },
      "amount": 54680.24,
      "date": "2022-3-1"
    },
    {
      "account": {
        "id": 3,
        "name": "GBM"
      },
      "amount": 12195,
      "date": "2022-3-1"
    },
    {
      "account": {
        "id": 2,
        "name": "Bitso"
      },
      "amount": 27275.61,
      "date": "2022-3-1"
    },
    {
      "account": {
        "id": 7,
        "name": "BRIQ"
      },
      "amount": 200000,
      "date": "2022-3-1"
    },
    {
      "account": {
        "id": 6,
        "name": "CETES"
      },
      "amount": 3000,
      "date": "2022-3-1"
    },
    {
      "account": {
        "id": 3,
        "name": "GBM"
      },
      "amount": 2000,
      "date": "2022-2-15"
    },
    {
      "account": {
        "id": 2,
        "name": "Bitso"
      },
      "amount": 5000,
      "date": "2022-3-1"
    },
    {
      "account": {
        "id": 3,
        "name": "GBM"
      },
      "amount": 2000,
      "date": "2022-3-1"
    },
    {
      "account": {
        "id": 2,
        "name": "Bitso"
      },
      "amount": 5000,
      "date": "2022-3-4"
    },
    {
      "account": {
        "id": 2,
        "name": "Bitso"
      },
      "amount": 4000,
      "date": "2022-3-4"
    },
    {
      "account": {
        "id": 1,
        "name": "LTB"
      },
      "amount": 1000207.76,
      "date": "2022-4-1"
    },
    {
      "account": {
        "id": 4,
        "name": "BANAMEX"
      },
      "amount": 12522.06,
      "date": "2022-4-1"
    },
    {
      "account": {
        "id": 5,
        "name": "SANTANDER"
      },
      "amount": 72460.96,
      "date": "2022-4-1"
    },
    {
      "account": {
        "id": 2,
        "name": "Bitso"
      },
      "amount": 44940.58,
      "date": "2022-4-1"
    },
    {
      "account": {
        "id": 3,
        "name": "GBM"
      },
      "amount": 14780.13,
      "date": "2022-4-1"
    },
    {
      "account": {
        "id": 6,
        "name": "CETES"
      },
      "amount": 6000,
      "date": "2022-4-1"
    },
    {
      "account": {
        "id": 7,
        "name": "BRIQ"
      },
      "amount": 200000,
      "date": "2022-4-1"
    },
    {
      "account": {
        "id": 2,
        "name": "Bitso"
      },
      "amount": 5000,
      "date": "2022-4-6"
    },
    {
      "account": {
        "id": 2,
        "name": "Bitso"
      },
      "amount": 5000,
      "date": "2022-4-10"
    },
    {
      "account": {
        "id": 2,
        "name": "Bitso"
      },
      "amount": 9500,
      "date": "2021-12-31"
    },
    {
      "account": {
        "id": 2,
        "name": "Bitso"
      },
      "amount": 5000,
      "date": "2022-4-11"
    },
    {
      "account": {
        "id": 1,
        "name": "LTB"
      },
      "amount": 1000961.28,
      "date": "2022-5-1"
    },
    {
      "account": {
        "id": 4,
        "name": "BANAMEX"
      },
      "amount": 9473.14,
      "date": "2022-5-1"
    },
    {
      "account": {
        "id": 5,
        "name": "SANTANDER"
      },
      "amount": 120683.83,
      "date": "2022-5-1"
    },
    {
      "account": {
        "id": 2,
        "name": "Bitso"
      },
      "amount": 52327.96,
      "date": "2022-5-1"
    },
    {
      "account": {
        "id": 3,
        "name": "GBM"
      },
      "amount": 13565.69,
      "date": "2022-5-1"
    },
    {
      "account": {
        "id": 7,
        "name": "BRIQ"
      },
      "amount": 200000,
      "date": "2022-5-1"
    },
    {
      "account": {
        "id": 6,
        "name": "CETES"
      },
      "amount": 9000,
      "date": "2022-5-1"
    },
    {
      "account": {
        "id": 5,
        "name": "SANTANDER"
      },
      "amount": 37922.62,
      "date": "2022-6-1"
    },
    {
      "account": {
        "id": 4,
        "name": "BANAMEX"
      },
      "amount": 18973.17,
      "date": "2022-6-1"
    },
    {
      "account": {
        "id": 1,
        "name": "LTB"
      },
      "amount": 1103472.41,
      "date": "2022-6-1"
    },
    {
      "account": {
        "id": 7,
        "name": "BRIQ"
      },
      "amount": 200000,
      "date": "2022-6-1"
    },
    {
      "account": {
        "id": 3,
        "name": "GBM"
      },
      "amount": 13740.43,
      "date": "2022-6-1"
    },
    {
      "account": {
        "id": 2,
        "name": "Bitso"
      },
      "amount": 49131.71,
      "date": "2022-6-1"
    },
    {
      "account": {
        "id": 2,
        "name": "Bitso"
      },
      "amount": 8000,
      "date": "2022-5-5"
    },
    {
      "account": {
        "id": 6,
        "name": "CETES"
      },
      "amount": 12154.63,
      "date": "2022-6-1"
    },
    {
      "account": {
        "id": 4,
        "name": "BANAMEX"
      },
      "amount": 20375.47,
      "date": "2022-7-1"
    },
    {
      "account": {
        "id": 1,
        "name": "LTB"
      },
      "amount": 1100000,
      "date": "2022-7-1"
    },
    {
      "account": {
        "id": 7,
        "name": "BRIQ"
      },
      "amount": 200000,
      "date": "2022-7-1"
    },
    {
      "account": {
        "id": 6,
        "name": "CETES"
      },
      "amount": 15244.99,
      "date": "2022-7-1"
    },
    {
      "account": {
        "id": 2,
        "name": "Bitso"
      },
      "amount": 30636.56,
      "date": "2022-7-1"
    },
    {
      "account": {
        "id": 3,
        "name": "GBM"
      },
      "amount": 12671.71,
      "date": "2022-7-1"
    },
    {
      "account": {
        "id": 5,
        "name": "SANTANDER"
      },
      "amount": 42058.58,
      "date": "2022-7-1"
    },
    {
      "account": {
        "id": 5,
        "name": "SANTANDER"
      },
      "amount": 72600.53,
      "date": "2022-8-1"
    },
    {
      "account": {
        "id": 4,
        "name": "BANAMEX"
      },
      "amount": 21866.82,
      "date": "2022-8-1"
    },
    {
      "account": {
        "id": 1,
        "name": "LTB"
      },
      "amount": 1100000,
      "date": "2022-8-1"
    },
    {
      "account": {
        "id": 7,
        "name": "BRIQ"
      },
      "amount": 200000,
      "date": "2022-8-1"
    },
    {
      "account": {
        "id": 2,
        "name": "Bitso"
      },
      "amount": 30636.56,
      "date": "2022-8-1"
    },
    {
      "account": {
        "id": 3,
        "name": "GBM"
      },
      "amount": 13712.98,
      "date": "2022-8-1"
    },
    {
      "account": {
        "id": 6,
        "name": "CETES"
      },
      "amount": 15244.99,
      "date": "2022-8-1"
    },
    {
      "account": {
        "id": 4,
        "name": "BANAMEX"
      },
      "amount": 60756.48,
      "date": "2022-9-1"
    },
    {
      "account": {
        "id": 1,
        "name": "LTB"
      },
      "amount": 1100000,
      "date": "2022-9-1"
    },
    {
      "account": {
        "id": 2,
        "name": "Bitso"
      },
      "amount": 31700.64,
      "date": "2022-9-1"
    },
    {
      "account": {
        "id": 3,
        "name": "GBM"
      },
      "amount": 13156.66,
      "date": "2022-9-1"
    },
    {
      "account": {
        "id": 7,
        "name": "BRIQ"
      },
      "amount": 148988.02,
      "date": "2022-9-1"
    },
    {
      "account": {
        "id": 6,
        "name": "CETES"
      },
      "amount": 21507.69,
      "date": "2022-9-1"
    },
    {
      "account": {
        "id": 5,
        "name": "SANTANDER"
      },
      "amount": 114322.39,
      "date": "2022-9-1"
    },
    {
      "account": {
        "id": 5,
        "name": "SANTANDER"
      },
      "amount": 155676.26,
      "date": "2022-10-1"
    },
    {
      "account": {
        "id": 1,
        "name": "LTB"
      },
      "amount": 1000000,
      "date": "2022-10-1"
    },
    {
      "account": {
        "id": 4,
        "name": "BANAMEX"
      },
      "amount": 177336.02,
      "date": "2022-10-1"
    },
    {
      "account": {
        "id": 6,
        "name": "CETES"
      },
      "amount": 24665.93,
      "date": "2022-10-1"
    },
    {
      "account": {
        "id": 7,
        "name": "BRIQ"
      },
      "amount": 137171.02,
      "date": "2022-10-1"
    },
    {
      "account": {
        "id": 2,
        "name": "Bitso"
      },
      "amount": 30595.86,
      "date": "2022-10-1"
    },
    {
      "account": {
        "id": 3,
        "name": "GBM"
      },
      "amount": 12159.31,
      "date": "2022-10-1"
    },
    {
      "account": {
        "id": 5,
        "name": "SANTANDER"
      },
      "amount": 110138,
      "date": "2022-11-1"
    },
    {
      "account": {
        "id": 1,
        "name": "LTB"
      },
      "amount": 1000000,
      "date": "2022-11-1"
    },
    {
      "account": {
        "id": 4,
        "name": "BANAMEX"
      },
      "amount": 162208.17,
      "date": "2022-11-1"
    },
    {
      "account": {
        "id": 6,
        "name": "CETES"
      },
      "amount": 128520.5,
      "date": "2022-11-1"
    },
    {
      "account": {
        "id": 7,
        "name": "BRIQ"
      },
      "amount": 120886.31,
      "date": "2022-11-1"
    },
    {
      "account": {
        "id": 2,
        "name": "Bitso"
      },
      "amount": 31798.5,
      "date": "2022-11-1"
    },
    {
      "account": {
        "id": 3,
        "name": "GBM"
      },
      "amount": 13066.99,
      "date": "2022-11-1"
    },
    {
      "account": {
        "id": 5,
        "name": "SANTANDER"
      },
      "amount": 46298.89,
      "date": "2022-12-1"
    },
    {
      "account": {
        "id": 1,
        "name": "LTB"
      },
      "amount": 1239000,
      "date": "2022-12-1"
    },
    {
      "account": {
        "id": 4,
        "name": "BANAMEX"
      },
      "amount": 11738.59,
      "date": "2022-12-1"
    },
    {
      "account": {
        "id": 6,
        "name": "CETES"
      },
      "amount": 129532.95,
      "date": "2022-12-1"
    },
    {
      "account": {
        "id": 7,
        "name": "BRIQ"
      },
      "amount": 121688.58,
      "date": "2022-12-1"
    },
    {
      "account": {
        "id": 2,
        "name": "Bitso"
      },
      "amount": 25761.54,
      "date": "2022-12-1"
    },
    {
      "account": {
        "id": 3,
        "name": "GBM"
      },
      "amount": 13791.67,
      "date": "2022-12-1"
    },
    {
      "account": {
        "id": 1,
        "name": "LTB"
      },
      "amount": 1264000,
      "date": "2022-1-1"
    },
    {
      "account": {
        "id": 2,
        "name": "Bitso"
      },
      "amount": 26136.15,
      "date": "2022-1-1"
    },
    {
      "account": {
        "id": 3,
        "name": "GBM"
      },
      "amount": 12988.3,
      "date": "2022-1-1"
    },
    {
      "account": {
        "id": 4,
        "name": "BANAMEX"
      },
      "amount": 12068.15,
      "date": "2022-1-1"
    },
    {
      "account": {
        "id": 5,
        "name": "SANTANDER"
      },
      "amount": 89030.49,
      "date": "2022-1-1"
    },
    {
      "account": {
        "id": 3,
        "name": "GBM"
      },
      "amount": 0,
      "date": "2022-1-1"
    },
    {
      "account": {
        "id": 7,
        "name": "BRIQ"
      },
      "amount": 120035.01,
      "date": "2022-1-1"
    },
    {
      "account": {
        "id": 6,
        "name": "CETES"
      },
      "amount": 130662.37,
      "date": "2022-1-1"
    },
    {
      "account": {
        "id": 1,
        "name": "LTB"
      },
      "amount": 1264000,
      "date": "2022-2-1"
    },
    {
      "account": {
        "id": 2,
        "name": "Bitso"
      },
      "amount": 35316.99,
      "date": "2022-2-1"
    },
    {
      "account": {
        "id": 3,
        "name": "GBM"
      },
      "amount": 14082.64,
      "date": "2022-2-1"
    },
    {
      "account": {
        "id": 4,
        "name": "BANAMEX"
      },
      "amount": 23157.37,
      "date": "2022-2-1"
    },
    {
      "account": {
        "id": 5,
        "name": "SANTANDER"
      },
      "amount": 162504.26,
      "date": "2022-2-1"
    },
    {
      "account": {
        "id": 6,
        "name": "CETES"
      },
      "amount": 131886.79,
      "date": "2022-2-1"
    },
    {
      "account": {
        "id": 7,
        "name": "BRIQ"
      },
      "amount": 108733.3,
      "date": "2022-2-1"
    },
    {
      "account": {
        "id": 1,
        "name": "LTB"
      },
      "amount": 1525000,
      "date": "2022-3-1"
    },
    {
      "account": {
        "id": 2,
        "name": "Bitso"
      },
      "amount": 31873.56,
      "date": "2022-3-1"
    },
    {
      "account": {
        "id": 3,
        "name": "GBM"
      },
      "amount": 13594.03,
      "date": "2022-3-1"
    },
    {
      "account": {
        "id": 4,
        "name": "BANAMEX"
      },
      "amount": 28461.23,
      "date": "2022-3-1"
    },
    {
      "account": {
        "id": 5,
        "name": "SANTANDER"
      },
      "amount": 69736.13,
      "date": "2022-3-1"
    },
    {
      "account": {
        "id": 6,
        "name": "CETES"
      },
      "amount": 0,
      "date": "2022-3-1"
    },
    {
      "account": {
        "id": 7,
        "name": "BRIQ"
      },
      "amount": 111800.88,
      "date": "2022-3-1"
    },
    {
      "account": {
        "id": 1,
        "name": "LTB"
      },
      "amount": 1525000,
      "date": "2022-4-1"
    },
    {
      "account": {
        "id": 2,
        "name": "Bitso"
      },
      "amount": 40512.67,
      "date": "2022-4-1"
    },
    {
      "account": {
        "id": 3,
        "name": "GBM"
      },
      "amount": 13886.86,
      "date": "2022-4-1"
    },
    {
      "account": {
        "id": 4,
        "name": "BANAMEX"
      },
      "amount": 57568.9,
      "date": "2022-4-1"
    },
    {
      "account": {
        "id": 5,
        "name": "SANTANDER"
      },
      "amount": 126373.07,
      "date": "2022-4-1"
    },
    {
      "account": {
        "id": 6,
        "name": "CETES"
      },
      "amount": 0,
      "date": "2022-4-1"
    },
    {
      "account": {
        "id": 7,
        "name": "BRIQ"
      },
      "amount": 61125.1,
      "date": "2022-4-1"
    },
    {
      "account": {
        "id": 1,
        "name": "LTB"
      },
      "amount": 1525000,
      "date": "2022-5-1"
    },
    {
      "account": {
        "id": 2,
        "name": "Bitso"
      },
      "amount": 40623.21,
      "date": "2022-5-1"
    },
    {
      "account": {
        "id": 3,
        "name": "GBM"
      },
      "amount": 13886.86,
      "date": "2022-5-1"
    },
    {
      "account": {
        "id": 4,
        "name": "BANAMEX"
      },
      "amount": 65044.77,
      "date": "2022-5-1"
    },
    {
      "account": {
        "id": 5,
        "name": "SANTANDER"
      },
      "amount": 211053.24,
      "date": "2022-5-1"
    },
    {
      "account": {
        "id": 6,
        "name": "CETES"
      },
      "amount": 0,
      "date": "2022-5-1"
    },
    {
      "account": {
        "id": 7,
        "name": "BRIQ"
      },
      "amount": 35287.73,
      "date": "2022-5-1"
    },
    {
      "account": {
        "id": 1,
        "name": "LTB"
      },
      "amount": 1525000,
      "date": "2022-6-1"
    },
    {
      "account": {
        "id": 2,
        "name": "Bitso"
      },
      "amount": 37546.22,
      "date": "2022-6-1"
    },
    {
      "account": {
        "id": 3,
        "name": "GBM"
      },
      "amount": 14499.23,
      "date": "2022-6-1"
    },
    {
      "account": {
        "id": 4,
        "name": "BANAMEX"
      },
      "amount": 25276.94,
      "date": "2022-6-1"
    },
    {
      "account": {
        "id": 5,
        "name": "SANTANDER"
      },
      "amount": 98933.48,
      "date": "2022-6-1"
    },
    {
      "account": {
        "id": 6,
        "name": "CETES"
      },
      "amount": 201867.06,
      "date": "2022-6-1"
    },
    {
      "account": {
        "id": 7,
        "name": "BRIQ"
      },
      "amount": 34596.16,
      "date": "2022-6-1"
    },
    {
      "account": {
        "id": 1,
        "name": "LTB"
      },
      "amount": 1525000,
      "date": "2022-7-1"
    },
    {
      "account": {
        "id": 2,
        "name": "Bitso"
      },
      "amount": 41892.52,
      "date": "2022-7-1"
    },
    {
      "account": {
        "id": 3,
        "name": "GBM"
      },
      "amount": 15229.4,
      "date": "2022-7-1"
    },
    {
      "account": {
        "id": 4,
        "name": "BANAMEX"
      },
      "amount": 15611.52,
      "date": "2022-7-1"
    },
    {
      "account": {
        "id": 5,
        "name": "SANTANDER"
      },
      "amount": 144858.37,
      "date": "2022-7-1"
    },
    {
      "account": {
        "id": 6,
        "name": "CETES"
      },
      "amount": 203717.19,
      "date": "2022-7-1"
    },
    {
      "account": {
        "id": 7,
        "name": "BRIQ"
      },
      "amount": 33892.98,
      "date": "2022-7-1"
    },
    {
      "account": {
        "id": 1,
        "name": "LTB"
      },
      "amount": 1525000,
      "date": "2022-8-1"
    },
    {
      "account": {
        "id": 2,
        "name": "Bitso"
      },
      "amount": 40035.57,
      "date": "2022-8-1"
    },
    {
      "account": {
        "id": 3,
        "name": "GBM"
      },
      "amount": 15229.4,
      "date": "2022-8-1"
    },
    {
      "account": {
        "id": 4,
        "name": "BANAMEX"
      },
      "amount": 5552.24,
      "date": "2022-8-1"
    },
    {
      "account": {
        "id": 5,
        "name": "SANTANDER"
      },
      "amount": 189530.31,
      "date": "2022-8-1"
    },
    {
      "account": {
        "id": 6,
        "name": "CETES"
      },
      "amount": 210868.07,
      "date": "2022-8-1"
    },
    {
      "account": {
        "id": 7,
        "name": "BRIQ"
      },
      "amount": 33901.66,
      "date": "2022-8-1"
    },
    {
      "account": {
        "id": 1,
        "name": "LTB"
      },
      "amount": 1399142,
      "date": "2022-9-1"
    },
    {
      "account": {
        "id": 2,
        "name": "Bitso"
      },
      "amount": 34676.27,
      "date": "2022-9-1"
    },
    {
      "account": {
        "id": 3,
        "name": "GBM"
      },
      "amount": 15229.4,
      "date": "2022-9-1"
    },
    {
      "account": {
        "id": 4,
        "name": "BANAMEX"
      },
      "amount": 14752.24,
      "date": "2022-9-1"
    },
    {
      "account": {
        "id": 5,
        "name": "SANTANDER"
      },
      "amount": 229092.24,
      "date": "2022-9-1"
    },
    {
      "account": {
        "id": 6,
        "name": "CETES"
      },
      "amount": 418437.79,
      "date": "2022-9-1"
    },
    {
      "account": {
        "id": 7,
        "name": "BRIQ"
      },
      "amount": 34230.24,
      "date": "2022-9-1"
    },
    {
      "account": {
        "id": 1,
        "name": "LTB"
      },
      "amount": 1413725.78,
      "date": "2022-10-1"
    },
    {
      "account": {
        "id": 2,
        "name": "Bitso"
      },
      "amount": 38674.76,
      "date": "2022-10-1"
    },
    {
      "account": {
        "id": 3,
        "name": "GBM"
      },
      "amount": 15229.4,
      "date": "2022-10-1"
    },
    {
      "account": {
        "id": 4,
        "name": "BANAMEX"
      },
      "amount": 14500.24,
      "date": "2022-10-1"
    },
    {
      "account": {
        "id": 5,
        "name": "SANTANDER"
      },
      "amount": 216354.52,
      "date": "2022-10-1"
    },
    {
      "account": {
        "id": 6,
        "name": "CETES"
      },
      "amount": 426908.48,
      "date": "2022-10-1"
    },
    {
      "account": {
        "id": 7,
        "name": "BRIQ"
      },
      "amount": 34585.26,
      "date": "2022-10-1"
    },
    {
      "account": {
        "id": 1,
        "name": "LTB"
      },
      "amount": 1417079.42,
      "date": "2022-11-1"
    },
    {
      "account": {
        "id": 7,
        "name": "BRIQ"
      },
      "amount": 34932.72,
      "date": "2022-11-1"
    },
    {
      "account": {
        "id": 3,
        "name": "GBM"
      },
      "amount": 14410,
      "date": "2022-11-1"
    },
    {
      "account": {
        "id": 4,
        "name": "BANAMEX"
      },
      "amount": 4000.25,
      "date": "2022-11-1"
    },
    {
      "account": {
        "id": 5,
        "name": "SANTANDER"
      },
      "amount": 139691.46,
      "date": "2022-11-1"
    },
    {
      "account": {
        "id": 6,
        "name": "CETES"
      },
      "amount": 587289.31,
      "date": "2022-11-1"
    },
    {
      "account": {
        "id": 1,
        "name": "LTB"
      },
      "amount": 1318676.04,
      "date": "2022-12-1"
    },
    {
      "account": {
        "id": 4,
        "name": "BANAMEX"
      },
      "amount": 19172.61,
      "date": "2022-12-1"
    },
    {
      "account": {
        "id": 5,
        "name": "SANTANDER"
      },
      "amount": 68156.99,
      "date": "2022-12-1"
    },
    {
      "account": {
        "id": 6,
        "name": "CETES"
      },
      "amount": 801206.87,
      "date": "2022-12-1"
    },
    {
      "account": {
        "id": 7,
        "name": "BRIQ"
      },
      "amount": 35276.03,
      "date": "2022-12-1"
    },
    {
      "account": {
        "id": 1,
        "name": "LTB"
      },
      "amount": 1321295.49,
      "date": "2024-1-1"
    },
    {
      "account": {
        "id": 4,
        "name": "BANAMEX"
      },
      "amount": 17103.61,
      "date": "2024-1-1"
    },
    {
      "account": {
        "id": 5,
        "name": "SANTANDER"
      },
      "amount": 127705.75,
      "date": "2024-1-1"
    },
    {
      "account": {
        "id": 6,
        "name": "CETES"
      },
      "amount": 813444.04,
      "date": "2024-1-1"
    },
    {
      "account": {
        "id": 7,
        "name": "BRIQ"
      },
      "amount": 35646.53,
      "date": "2024-1-1"
    },
    {
      "account": {
        "id": 1,
        "name": "LTB"
      },
      "amount": 1323667.77,
      "date": "2024-2-1"
    },
    {
      "account": {
        "id": 4,
        "name": "BANAMEX"
      },
      "amount": 17394.39,
      "date": "2024-2-1"
    },
    {
      "account": {
        "id": 5,
        "name": "SANTANDER"
      },
      "amount": 65964.68,
      "date": "2024-2-1"
    },
    {
      "account": {
        "id": 6,
        "name": "CETES"
      },
      "amount": 978353.56,
      "date": "2024-2-1"
    },
    {
      "account": {
        "id": 7,
        "name": "BRIQ"
      },
      "amount": 35986.43,
      "date": "2024-2-1"
    },
    {
      "account": {
        "id": 1,
        "name": "LTB"
      },
      "amount": 1325996.94,
      "date": "2024-3-1"
    },
    {
      "account": {
        "id": 4,
        "name": "BANAMEX"
      },
      "amount": 19390.51,
      "date": "2024-3-1"
    },
    {
      "account": {
        "id": 5,
        "name": "SANTANDER"
      },
      "amount": 50594.49,
      "date": "2024-3-1"
    },
    {
      "account": {
        "id": 6,
        "name": "CETES"
      },
      "amount": 990983.47,
      "date": "2024-3-1"
    },
    {
      "account": {
        "id": 7,
        "name": "BRIQ"
      },
      "amount": 33974.39,
      "date": "2024-3-1"
    },
    {
      "account": {
        "id": 8,
        "name": "NU"
      },
      "amount": 40050,
      "date": "2024-3-1"
    },
    {
      "account": {
        "id": 1,
        "name": "LTB"
      },
      "amount": 1328478.89,
      "date": "2024-4-1"
    },
    {
      "account": {
        "id": 4,
        "name": "BANAMEX"
      },
      "amount": 15593.66,
      "date": "2024-4-1"
    },
    {
      "account": {
        "id": 5,
        "name": "SANTANDER"
      },
      "amount": 85392.22,
      "date": "2024-4-1"
    },
    {
      "account": {
        "id": 6,
        "name": "CETES"
      },
      "amount": 1004742.79,
      "date": "2024-4-1"
    },
    {
      "account": {
        "id": 7,
        "name": "BRIQ"
      },
      "amount": 27135.5,
      "date": "2024-4-1"
    },
    {
      "account": {
        "id": 8,
        "name": "NU"
      },
      "amount": 40587.54,
      "date": "2024-4-1"
    },
    {
      "account": {
        "id": 1,
        "name": "LTB"
      },
      "amount": 1330906.92,
      "date": "2024-5-1"
    },
    {
      "account": {
        "id": 4,
        "name": "BANAMEX"
      },
      "amount": 7674.32,
      "date": "2024-5-1"
    },
    {
      "account": {
        "id": 5,
        "name": "SANTANDER"
      },
      "amount": 92732.17,
      "date": "2024-5-1"
    },
    {
      "account": {
        "id": 6,
        "name": "CETES"
      },
      "amount": 1016832.16,
      "date": "2024-5-1"
    },
    {
      "account": {
        "id": 7,
        "name": "BRIQ"
      },
      "amount": 24107.41,
      "date": "2024-5-1"
    },
    {
      "account": {
        "id": 8,
        "name": "NU"
      },
      "amount": 81601,
      "date": "2024-5-1"
    },
    {
      "account": {
        "id": 1,
        "name": "LTB"
      },
      "amount": 1333220.1,
      "date": "2024-6-1"
    },
    {
      "account": {
        "id": 4,
        "name": "BANAMEX"
      },
      "amount": 7174.32,
      "date": "2024-6-1"
    },
    {
      "account": {
        "id": 5,
        "name": "SANTANDER"
      },
      "amount": 61628.51,
      "date": "2024-6-1"
    },
    {
      "account": {
        "id": 6,
        "name": "CETES"
      },
      "amount": 1031137.85,
      "date": "2024-6-1"
    },
    {
      "account": {
        "id": 7,
        "name": "BRIQ"
      },
      "amount": 24347.37,
      "date": "2024-6-1"
    },
    {
      "account": {
        "id": 8,
        "name": "NU"
      },
      "amount": 143356.88,
      "date": "2024-6-1"
    },
    {
      "account": {
        "id": 1,
        "name": "LTB"
      },
      "amount": 1335682.12,
      "date": "2024-7-1"
    },
    {
      "account": {
        "id": 4,
        "name": "BANAMEX"
      },
      "amount": 6674.32,
      "date": "2024-7-1"
    },
    {
      "account": {
        "id": 5,
        "name": "SANTANDER"
      },
      "amount": 61942.79,
      "date": "2024-7-1"
    },
    {
      "account": {
        "id": 6,
        "name": "CETES"
      },
      "amount": 1013636.6,
      "date": "2024-7-1"
    },
    {
      "account": {
        "id": 7,
        "name": "BRIQ"
      },
      "amount": 22568.99,
      "date": "2024-7-1"
    },
    {
      "account": {
        "id": 8,
        "name": "NU"
      },
      "amount": 195706.97,
      "date": "2024-7-1"
    }
  ]
}